puppetparser/.gitignore
puppetparser/__init__.py
puppetparser/__main__.py
puppetparser/model.py
puppetparser/parser.py
puppetparser-0.2.14.dist-info/LICENSE
puppetparser-0.2.14.dist-info/METADATA
puppetparser-0.2.14.dist-info/WHEEL
puppetparser-0.2.14.dist-info/RECORD
