Metadata-Version: 2.1
Name: puppetparser
Version: 0.2.14
Summary: A parser from Puppet to an object model
License: GPL-3.0
Keywords: puppet,parser,object model
Author: Nuno Saavedra
Author-email: nuno.saavedra@tecnico.ulisboa.pt
Requires-Python: >=3.9,<4.0
Classifier: Development Status :: 4 - Beta
Classifier: Intended Audience :: Developers
Classifier: License :: OSI Approved :: GNU General Public License v3 (GPLv3)
Classifier: Programming Language :: Python :: 3
Classifier: Programming Language :: Python :: 3.9
Classifier: Programming Language :: Python :: 3.10
Classifier: Programming Language :: Python :: 3.11
Classifier: Programming Language :: Python :: 3.12
Classifier: Programming Language :: Python :: 3 :: Only
Classifier: Topic :: Software Development :: Build Tools
Requires-Dist: ply (==3.11)
Project-URL: Bug Reports, https://github.com/Nfsaavedra/puppetparser/issues
Project-URL: Source, https://github.com/Nfsaavedra/puppetparser
